spreadsheet/__init__.py
spreadsheet/googlesheet.py
spreadsheet/spreadsheet.py
spreadsheet/tableediting.py
spreadsheet/version.py
pygenericspreadsheet-0.5.0.dist-info/METADATA
pygenericspreadsheet-0.5.0.dist-info/WHEEL
pygenericspreadsheet-0.5.0.dist-info/licenses/LICENSE
pygenericspreadsheet-0.5.0.dist-info/RECORD
