Metadata-Version: 2.4
Name: PyGenericSpreadSheet
Version: 0.5.0
Dynamic: Summary
Project-URL: Home, https://github.com/WolfgangFahl/PyGenericSpreadSheet/
Project-URL: Documentation, https://wiki.bitplan.com/index.php/PyGenericSpreadSheet
Project-URL: Source, https://github.com/WolfgangFahl/PyGenericSpreadSheet/
Author-email: Wolfgang Fahl <wf@bitplan.com>
Maintainer-email: Wolfgang Fahl <wf@bitplan.com>
License-Expression: Apache-2.0
License-File: LICENSE
Classifier: Development Status :: 4 - Beta
Classifier: Environment :: Web Environment
Classifier: Intended Audience :: Developers
Classifier: Intended Audience :: Education
Classifier: Intended Audience :: Science/Research
Classifier: License :: OSI Approved :: Apache Software License
Classifier: Operating System :: OS Independent
Classifier: Programming Language :: Python :: 3 :: Only
Classifier: Programming Language :: Python :: 3.10
Classifier: Programming Language :: Python :: 3.11
Classifier: Programming Language :: Python :: 3.12
Classifier: Programming Language :: Python :: 3.13
Classifier: Topic :: Software Development :: User Interfaces
Requires-Python: >=3.10
Requires-Dist: gspread>=6.0.2
Requires-Dist: odfpy>=1.4.1
Requires-Dist: openpyxl>=3.1.2
Requires-Dist: pandas>=2.2.1
Requires-Dist: py-ez-wikidata>=0.3.1
Requires-Dist: pylodstorage>=0.16.4
Requires-Dist: python-dateutil>=2.8.2
Requires-Dist: xlsxwriter>=3.2.0
Provides-Extra: test
Requires-Dist: green; extra == 'test'
